Metadata-Version: 1.0
Name: create-argparse-project
Version: 0.1.0
Summary: Create new click project
Home-page: https://git
Author: Hibikine Kage
Author-email: mail@hibikine.me
License: MIT
Platform: UNKNOWN
